README.md
setup.py
dockter/__init__.py
dockter/dockter.py
dockter.egg-info/PKG-INFO
dockter.egg-info/SOURCES.txt
dockter.egg-info/dependency_links.txt
dockter.egg-info/entry_points.txt
dockter.egg-info/top_level.txt