Metadata-Version: 2.1
Name: dockter
Version: 0.1.8
Summary: A package to create dockerfiles for jupyter notebooks to ensure compatibility
Home-page: https://github.com/sjmignot/dockter.nb
Author: Samuel Mignot
License: UNKNOWN
Platform: UNKNOWN
Classifier: Programming Language :: Python :: 3
Classifier: License :: OSI Approved :: MIT License
Classifier: Operating System :: OS Independent
Requires-Python: >=3.6
